README.md
setup.py
bi_s3/__init__.py
bi_s3/bi_s3.py
bi_s3/biz_intel_creds.py
bi_s3.egg-info/PKG-INFO
bi_s3.egg-info/SOURCES.txt
bi_s3.egg-info/dependency_links.txt
bi_s3.egg-info/top_level.txt