Metadata-Version: 1.1
Name: bi-s3
Version: 0.2.2
Summary: S3 connector package designed to make data lake operations easier for PitchBook Business Intelligence
Home-page: https://git.pitchbookdata.com/business-intelligence/bi_s3
Author: BI Data Engineering
Author-email: jun.kim@pitchbook.com
License: UNKNOWN
Platform: UNKNOWN
Classifier: Programming Language :: Python :: 2
Classifier: Programming Language :: Python :: 3
Classifier: License :: OSI Approved :: MIT License
Classifier: Operating System :: OS Independent
